._GKextCPy.cpp
._GKextCPy.h
GKextCPy.cpp
GKextCPy.h
GKextCPy.i
GKextCPy.py
GKextCPy_wrap.cxx
MANIFEST
MANIFEST.in
eigen.i
numpy.i
setup.py
GKextCPy.egg-info/PKG-INFO
GKextCPy.egg-info/SOURCES.txt
GKextCPy.egg-info/dependency_links.txt
GKextCPy.egg-info/requires.txt
GKextCPy.egg-info/top_level.txt