Metadata-Version: 1.0
Name: GKextCPy
Version: 0.3.9
Summary: Graph Kernels: building the extension Python module. This is a wrapper package from C++ to Python.
Home-page: UNKNOWN
Author: Elisabetta Ghisu
Author-email: UNKNOWN
License: ETH Zurich
Platform: UNKNOWN
